wda/__init__.py
wda/_proto.py
wda/exceptions.py
wda/utils.py
wda/xcui_element_types.py
wda/usbmux/__init__.py
wda/usbmux/exceptions.py
wda/usbmux/pyusbmux.py
facebook_wda-1.5.4.dist-info/AUTHORS
facebook_wda-1.5.4.dist-info/LICENSE
facebook_wda-1.5.4.dist-info/METADATA
facebook_wda-1.5.4.dist-info/WHEEL
facebook_wda-1.5.4.dist-info/pbr.json
facebook_wda-1.5.4.dist-info/top_level.txt
facebook_wda-1.5.4.dist-info/RECORD
